Workbook

Sheet Cover
A2: FINOSUTRA
A6: Finance on Autopilot · finosutra.github.io
A10: Income Tax Computation Report
A12: Financial Year 2025-26 | Assessment Year 2026-27
A13: TAXPAYER DETAILS
A14: Taxpayer Name | C14: Rajesh Kumar Sharma
A15: PAN | C15: ABCRS1234K
A16: Date of Birth | C16: 15-Jun-1985
A17: Age (as on 31-Mar-26) | C17: 40
A18: Residential Status | C18: Resident Individual
A19: Taxpayer Category | C19: Individual (Below 60)
A20: Assessment Year | C20: 2026-27
A21: Report Date | C21: 30-May-2026
A22: TAX SUMMARY
A23: Gross Total Income | D23: ='Income Schedule'!D35 -> 15314000
A24: Total Deductions (Old) | D24: =Deductions!D30 -> 0
A25: Recommended Regime | D25: New Tax Regime
A26: Tax — New Regime | D26: ='Tax Computation'!D42 -> 0
A27: Tax — Old Regime | D27: ='Tax Computation'!H42 -> 0
A28: Tax Saving (New vs Old) | D28: ='Tax Computation'!D46 -> 0
A29: Net Tax Payable / Refund | D29: ='Tax Computation'!D50 -> 0
A31: ⚠ This report is for estimation purposes only. Consult a qualified CA/Tax Advisor for official filing. Generated by Finosutra (finosutra.github.io)
A33: COLOR LEGEND
A34: ● Blue text | C34: Hardcoded inputs — values you entered in the calculator
A35: ● Black text | C35: Formula-driven calculations — update automatically
A36: ● Green text | C36: Links from other sheets — live cross-references

Sheet Income Schedule
A1: INCOME SCHEDULE | FY 2025-26 | AY 2026-27
A2: HEAD OF INCOME | B2: NOTES | C2: NEW REGIME (₹) | D2: OLD REGIME (₹)
A3: A. INCOME FROM SALARY
A4: Gross Salary (CTC basis) | B4: 15,00,000 | C4: 15000000 | D4: 15000000
A5: Less: HRA Exemption [Sec 10(13A)] | B5: See Note 1 | C5: 0 | D5: -150000
A6: Less: Standard Deduction [Sec 16(ia)] | B6: ₹75,000 / ₹50,000 | C6: -75000 | D6: -50000
A7: Less: Professional Tax [Sec 16(iii)] | B7: Actual | C7: 0 | D7: -2400
A8: Net Taxable Salary | C8: =SUM(C4:C7) -> 14925000 | D8: =SUM(D4:D7) -> 14797600
A10: B. INCOME FROM HOUSE PROPERTY
A11: Annual Rent Received (LOP) | B11: Actual | C11: 0 | D11: 240000
A12: Less: Municipal Tax Paid | B12: Actual | C12: 0 | D12: -12000
A13: Net Annual Value (NAV) | B13: Rent minus Municipal Tax | C13: =0 -> 0 | D13: =D11-D12 -> 252000
A14: Less: Standard Deduction (30%) | B14: NAV x 30% | C14: =0 -> 0 | D14: =-D13*0.3 -> -75600
A15: Less: Interest on Loan (LOP) | B15: Actual | C15: 0 | D15: 0
A16: Less: Interest on Loan (SOP) | B16: Max ₹2L | C16: 0 | D16: -200000
A17: Income from House Property | C17: =SUM(C11:C16) -> 0 | D17: =SUM(D11:D16) -> 204400
A19: C. CAPITAL GAINS
A20: Equity LTCG (above ₹1,25,000 exempt) | B20: 12.5% flat | C20: 250000 | D20: 250000
A21: Equity STCG | B21: 20% flat | C21: 0 | D21: 0
A22: Property LTCG | B22: 12.5% / 20% | C22: 0 | D22: 0
A23: Other Short-Term Gains (slab rate) | B23: Normal slab | C23: 0 | D23: 0
A24: Total Capital Gains | C24: =SUM(C20:C23) -> 250000 | D24: =SUM(D20:D23) -> 250000
A26: D. INCOME FROM OTHER SOURCES
A27: Savings Account Interest | B27: 80TTA: max ₹10K | C27: 12000 | D27: 12000
A28: FD Interest | B28: Taxable in full | C28: 50000 | D28: 50000
A29: Dividend Income | B29: Taxable | C29: 0 | D29: 0
A30: Any Other Income | B30: Taxable | C30: 0 | D30: 0
A31: Total Other Sources | C31: =SUM(C27:C30) -> 62000 | D31: =SUM(D27:D30) -> 62000
A35: GROSS TOTAL INCOME | C35: =C8+C17+C24+C31 -> 15237000 | D35: =D8+D17+D24+D31 -> 15314000

Sheet Deductions
A1: DEDUCTIONS SCHEDULE | Chapter VI-A | Old Regime Only
A2: SECTION / DEDUCTION | B2: LIMIT / NOTES | C2: ENTERED (₹) | D2: ALLOWED (₹)
A3: 80C — EPF / PPF / ELSS / LIC / Tax-saver FD
A4: EPF | B4: Actual | C4: 60000 | D4: =C4 -> 60000
A5: PPF | B5: Actual | C5: 50000 | D5: =C5 -> 50000
A6: ELSS Mutual Fund | B6: Actual | C6: 40000 | D6: =C6 -> 40000
A7: Life Insurance | B7: Actual | C7: 20000 | D7: =C7 -> 20000
A8: Sub-total 80C | B8: Max ₹1,50,000 | D8: =MIN(SUM(C4:C7),150000) -> 150000
A9: 80CCD — NPS
A10: 80CCD(1B) — Additional NPS | B10: Max ₹50,000 | C10: 30000 | D10: =C10 -> 30000
A11: 80CCD(2) — Employer NPS | B11: Max 10% of Basic | C11: 50000 | D11: =C11 -> 50000
A12: Sub-total 80CCD | B12: 1B: max ₹50,000 | D12: =MIN(C9,50000)+C10 -> 80000
A13: 80D — Medical Insurance
A14: Self / Spouse / Children | B14: Max ₹25,000 | C14: 20000 | D14: =C14 -> 20000
A15: Parents | B15: Max ₹25,000 | C15: 15000 | D15: =C15 -> 15000
A16: Sub-total 80D | B16: ₹25K+₹25K | D16: =MIN(C13,25000)+MIN(C14,25000) -> 45000
A17: Other Deductions
A18: 80E — Education Loan Interest | B18: No limit | C18: 0 | D18: =C18 -> 0
A19: 80TTA — Savings Interest | B19: Max ₹10,000 | C19: 10000 | D19: =C19 -> 10000
A20: 80G — Donations | B20: 50% of qualifying | C20: 5000 | D20: =C20 -> 5000
A21: Sub-total Others | D21: =C17+MIN(C18,10000)+C19*0.5 -> 5000
A22: TOTAL DEDUCTIONS (Old Regime) | B22: Sum of all sections | D22: =D8+D11+D15+D20 -> 220000
A24: Note: Deductions in the New Regime are restricted to 80CCD(2) (Employer NPS) and Standard Deduction only.

Sheet Tax Computation
A1: TAX COMPUTATION | New Regime vs Old Regime | FY 2025-26
A2: PARTICULARS | B2: NOTES | C2: NEW REGIME | F2: OLD REGIME | I2: DIFFERENCE (OLD − NEW)
A3: INCOME
A4: Gross Total Income | B4: From Income Schedule | C4: ='Income Schedule'!C35 -> 15237000 | F4: ='Income Schedule'!D35 -> 15314000 | I4: =F4-C4 -> 77000
A5: Less: Total Deductions | B5: Ch VI-A (Old only) | C5: =Deductions!D10*0 -> 0 | F5: =-Deductions!D30 -> 0 | I5: =F5-C5 -> 0
A6: Taxable Income | C6: =C4+C5 -> 15237000 | F6: =F4+F5 -> 15314000 | I6: =F6-C6 -> 77000
A8: SLAB TAX
A9: Tax on Normal Slab Income | B9: Per slab schedule | C9: 117500 | F9: 262500 | I9: =F9-C9 -> 145000
A10: Tax on Capital Gains (12.5% LTCG) | B10: LTCG >₹1.25L | C10: =('Income Schedule'!C20-125000)*0.125 -> 15625 | F10: =('Income Schedule'!D20-125000)*0.125 -> 15625 | I10: =F10-C10 -> 0
A11: Total Tax Before Rebate | C11: =C9+C10 -> 133125 | F11: =F9+F10 -> 278125 | I11: =F11-C11 -> 145000
A13: REBATE & RELIEF
A14: Less: Rebate u/s 87A | B14: New: 0 (income>12L) / Old: ₹12,500 if ≤₹5L | C14: 0 | F14: =IF(F10<=500000,MIN(F12,12500),0) -> 12500 | I14: =F14-C14 -> 12500
A15: Tax After Rebate | C15: =C12-C14 -> 0 | F15: =F12-F14 -> -12500 | I15: =F15-C15 -> -12500
A17: SURCHARGE & CESS
A18: Add: Surcharge | B18: Nil (income < ₹50L) | C18: 0 | F18: 0 | I18: =F18-C18 -> 0
A19: Add: Health & Education Cess @4% | B19: 4% on tax+surcharge | C19: =C17*0.04 -> 0 | F19: =F17*0.04 -> 0 | I19: =F19-C19 -> 0
A21: TOTAL TAX LIABILITY | B21: Tax + Surcharge + Cess | C21: =C18+C19+C20 -> 0 | F21: =F18+F19+F20 -> 0 | I21: =F21-C21 -> 0
A23: SAVINGS & TAX CREDITS
A24: Tax Saving (New Regime vs Old) | B24: Positive = New regime is cheaper | C24: =F21-C21 -> 0 | I24: =F24-C24 -> 0
A25: Less: TDS Deducted (Salary + Other) | B25: From Form 26AS | C25: -90000 | F25: -90000 | I25: =F25-C25 -> 0
A26: Less: Advance Tax Paid | C26: 0 | F26: 0 | I26: =F26-C26 -> 0
A27: Net Tax Payable / (Refund) | C27: =C21+C25+C26 -> -90000 | F27: =F21+F25+F26 -> -90000 | I27: =F27-C27 -> 0

Sheet Slab Schedule
A1: TAX SLAB SCHEDULE | FY 2025-26 | AY 2026-27
A2: NEW TAX REGIME — Tax Slabs
A3: INCOME RANGE | B3: FROM (₹) | C3: TO (₹) | D3: RATE %
A4: Nil | B4: 0 | C4: 400000 | D4: 0%
A5: 5% | B5: 400001 | C5: 800000 | D5: 5%
A6: 10% | B6: 800001 | C6: 1200000 | D6: 10%
A7: 15% | B7: 1200001 | C7: 1600000 | D7: 15%
A8: 20% | B8: 1600001 | C8: 2000000 | D8: 20%
A9: 25% | B9: 2000001 | C9: 2400000 | D9: 25%
A10: 30% | B10: 2400001 | C10: Above | D10: 30%
A13: ✓ Standard Deduction: ₹75,000 (New Regime) | ₹50,000 (Old Regime)
A14: ✓ Rebate u/s 87A: Full tax rebate if taxable income ≤ ₹12,00,000 (New) | ₹5,00,000 (Old)
A15: ✓ Equity LTCG taxed at 12.5% on gains above ₹1,25,000 (both regimes)
A16: ✓ Equity STCG taxed at 20% flat (both regimes)
A17: ✓ Surcharge: Applicable above ₹50L income. Cess: 4% on all tax.
A18: ✓ Surcharge on LTCG capped at 15%
